{
	"node": "n8n-nodes-cloudflare.cloudflareTunnels",
	"nodeVersion": "1.0",
	"codexVersion": "1.0",
	"categories": ["Miscellaneous", "Development"],
	"subcategories": { "Miscellaneous": ["Networking", "Zero Trust"] },
	"alias": ["tunnels", "tunnel", "cloudflared", "cloudflare", "argo-tunnel"],
	"resources": {
		"credentialDocumentation": [{ "url": "https://developers.cloudflare.com/fundamentals/api/get-started/create-token/" }],
		"primaryDocumentation": [{ "url": "https://github.com/Automations-Project/n8n-nodes-cloudflare" }]
	}
}
